{
  "title": "좌청룡 우백호",
  "author": "루웨인 인문철학팀 (최공명 외)",
  "year": 2025,
  "language": "ko",
  "kdc": "100.4",
  "luwain_code": "100.43",
  "category": "언어철학·상징인류학",
  "summary_short": "《좌청룡 우백호》는 동서 상징체계의 구조와 언어를 비교하며, 인간 문화의 근원적 양극성을 루웨인 감응철학으로 재해석한 저작이다.",
  "summary_long": "좌청룡과 우백호는 단순한 신화가 아니라 인간 언어의 이중적 구조를 상징한다. 루웨인은 이 책에서 동서 문명의 상징과 언어의 생성 원리를 비교하며, '언어는 힘이자 방향이다'라는 테제를 전개한다. 권력, 신화, 종교, 정치, 예술의 이면에 작동하는 상징적 구조를 감응철학의 언어로 해석하고, 루웨인 트리니티의 언어적 토대를 마련한다.",
  "price": "5000원",
  "tags": ["언어", "상징", "문화", "철학", "인문", "루웨인", "감응"],
  "series": "루웨인 인문철학 시리즈 제1권",
  "path": "/goods/library/books/100.43_좌청룡_우백호/"
}
